datoso_seed_enhanced/__init__.py
datoso_seed_enhanced/actions.py
datoso_seed_enhanced/dats.py
datoso_seed_enhanced/fetch.py
datoso_seed_enhanced/rules.py
datoso_seed_enhanced-1.1.0.dist-info/LICENSE
datoso_seed_enhanced-1.1.0.dist-info/METADATA
datoso_seed_enhanced-1.1.0.dist-info/WHEEL
datoso_seed_enhanced-1.1.0.dist-info/top_level.txt
datoso_seed_enhanced-1.1.0.dist-info/RECORD
