Metadata-Version: 2.1
Name: datoso-seed-enhanced
Version: 1.1.0
Summary: Python command line tool to download and organize your Rom Dat files.
Author-email: Lacides Miranda <laromicas@hotmail.com>
License: MIT License
Project-URL: Source Code, https://github.com/laromicas/datoso_seed_enhanced
Keywords: emulators,roms
Classifier: Development Status :: 4 - Beta
Classifier: Environment :: Console
Classifier: License :: OSI Approved :: MIT License
Classifier: Operating System :: POSIX :: Linux
Classifier: Programming Language :: Python :: 3
Classifier: Topic :: System :: Emulators
Requires-Python: >=3.11
License-File: LICENSE
Requires-Dist: datoso (>=1.1.0)
Requires-Dist: datoso-plugin-internetarchive (>=1.1.1)
